nsaproxy/__init__.py
nsaproxy/classes/__init__.py
nsaproxy/classes/apis.py
nsaproxy/classes/common.py
nsaproxy/classes/config.py
nsaproxy/modules/__init__.py
nsaproxy/modules/pdns.py
nsaproxy/plugins/__init__.py
nsaproxy/plugins/cdns.py
nsaproxy/plugins/r53.py
nsaproxy-0.1.58.data/scripts/nsaproxy
nsaproxy-0.1.58.dist-info/LICENSE
nsaproxy-0.1.58.dist-info/METADATA
nsaproxy-0.1.58.dist-info/WHEEL
nsaproxy-0.1.58.dist-info/top_level.txt
nsaproxy-0.1.58.dist-info/RECORD
